{"website": "www.triogentlerain.co.kr", "intro": "젠틀레인(Gentle Rain)은 2004년 드러머 서덕원에 의해 결성되어 재즈는 '지루하고 어렵다'는 장르에 대한 편견을 지워주는 서정적이고 편안한 선율로 2005년 1집 “Into The Gentle Rain”, 2007년 1.5집에 해당하는 영화음악 리메이크 앨범 “소나기 프로젝트”- “Cinema In Jazz”, 2008년 2집 “Second Rain”, 2010년 3집 앨범 “Dreams”, 2012년 4집 “Wish”, 2015년 ‘Home’을 국내 재즈 밴드로는 최고의 음반 판매고를 올리며 한국의 대표적인 재즈 트리오로 자리잡았다. \n\n젠틀레인은 ‘가장 한국적인 재즈’를 선보인다는 모토로 대중과의 접점을 넓히려는 행보를 이어가며 지난 10여 년간 우리네 삶과 가까이 맞닿아 있는 일상적인 주제의 곡을 선보이며, 재즈를 ‘쉽고 재미 있는’ 음악으로 인식을 바꾸는데 많은 기여를 해왔다.", "genre": "Jazz", "event": [{"venue_id": 910, "title": "2016 봄에 내리는 젠틀레인 / Love Songs For You", "date": "2016-04-30", "price": "R석 55,000원 / S석 44,000원 / A석 33,000원", "time": "18:00", "venue": "마포아트센터 아트홀맥", "lineup": [{"name": "젠틀 레인", "musician_id": 1943}]}, {"venue_id": 83, "title": "젠틀 레인 단독 공연", "date": "2012-08-10", "time": "20:00", "venue": "벨로주 (VELOSO)", "lineup": [{"name": "젠틀 레인", "musician_id": 1943}]}], "album": [{"albumtitle": "Gentle Rain 1집 - Into The Gentle Rain (2005, Kang & Music) (2005)"}], "regular_musician": [{"name": "젠틀 레인", "musician_id": 1943, "event_count": 2}], "name": "젠틀 레인", "musician_id": 1943, "member": "서덕원(드럼), 송지훈(피아노), 김호철(베이스)", "video": ["https://youtu.be/AEOUMcQ_tDE"]}