{"genre": "Rock", "event": [{"venue_id": 51, "title": "함께하는 시간에 대하여", "date": "2013-10-11", "price": "예매 10,000 현매12,000", "time": "20:00", "venue": "카페 언플러그드 (Cafe Unplugged)", "lineup": [{"name": "아를", "musician_id": 1384}, {"name": "je'she", "musician_id": 2380}, {"name": "플레이모드", "musician_id": 2581}, {"name": "대현", "musician_id": 2629}]}, {"venue_id": 51, "title": "다락방 음악회", "date": "2013-07-26", "time": "20:00", "venue": "카페 언플러그드 (Cafe Unplugged)", "lineup": [{"name": "노르딕", "musician_id": 600}, {"name": "나인어클락", "musician_id": 2041}, {"name": "je'she", "musician_id": 2380}]}, {"venue_id": 408, "title": "깨방정 기획공연 Vol.3", "date": "2013-03-14", "price": "10000", "time": "21:00", "venue": "깨방정", "lineup": [{"name": "je'she", "musician_id": 2380}, {"name": "호소", "musician_id": 2389}, {"name": "오로라스팅", "musician_id": 2390}]}, {"venue_id": 51, "title": "불어라 봄바람", "date": "2013-03-09", "price": "예매1만원,현매12천원", "time": "19:00", "venue": "카페 언플러그드 (Cafe Unplugged)", "lineup": [{"name": "솔솔부는 봄바람", "musician_id": 334}, {"name": "이루리 프로젝트", "musician_id": 496}, {"name": "je'she", "musician_id": 2380}]}, {"venue_id": 393, "title": "Club TA Busking Night", "date": "2013-02-21", "time": "19:00", "venue": "클럽 타(Club TA)", "lineup": [{"name": "렘수면상태의밴드", "musician_id": 2075}, {"name": "곤", "musician_id": 2329}, {"name": "je'she", "musician_id": 2380}, {"name": "오로라스팅", "musician_id": 2390}, {"name": "신현희와 김루트", "musician_id": 2586}]}, {"venue_id": 51, "title": "금요일밤의 어쿠스틱!", "date": "2013-01-04", "price": "예매 9천원,현매1만원", "time": "20:00", "venue": "카페 언플러그드 (Cafe Unplugged)", "lineup": [{"name": "블랙러시안", "musician_id": 1060}, {"name": "je'she", "musician_id": 2380}, {"name": "플랫핏", "musician_id": 2404}]}, {"venue_id": 280, "title": "감성달빛 오픈마이크", "date": "2012-11-20", "time": "20:00", "venue": "감성달빛", "lineup": [{"name": "락쿤", "musician_id": 291}, {"name": "죄다 커플", "musician_id": 582}, {"name": "je'she", "musician_id": 2380}, {"name": "soup/숲", "musician_id": 3341}]}, {"venue_id": 57, "title": "목요일 live", "date": "2012-11-08", "time": "20:30", "venue": "디디다 (Cafe DD.DA)", "lineup": [{"name": "je'she", "musician_id": 2380}, {"name": "쥴라이마일스", "musician_id": 2381}]}], "regular_musician": [{"name": "je'she", "musician_id": 2380, "event_count": 8}, {"name": "오로라스팅", "musician_id": 2390, "event_count": 2}, {"name": "락쿤", "musician_id": 291, "event_count": 1}, {"name": "블랙러시안", "musician_id": 1060, "event_count": 1}, {"name": "대현", "musician_id": 2629, "event_count": 1}, {"name": "죄다 커플", "musician_id": 582, "event_count": 1}, {"name": "아를", "musician_id": 1384, "event_count": 1}, {"name": "플랫핏", "musician_id": 2404, "event_count": 1}, {"name": "soup/숲", "musician_id": 3341, "event_count": 1}, {"name": "솔솔부는 봄바람", "musician_id": 334, "event_count": 1}, {"name": "쥴라이마일스", "musician_id": 2381, "event_count": 1}, {"name": "이루리 프로젝트", "musician_id": 496, "event_count": 1}, {"name": "플레이모드", "musician_id": 2581, "event_count": 1}, {"name": "곤", "musician_id": 2329, "event_count": 1}, {"name": "노르딕", "musician_id": 600, "event_count": 1}, {"name": "나인어클락", "musician_id": 2041, "event_count": 1}, {"name": "신현희와 김루트", "musician_id": 2586, "event_count": 1}, {"name": "렘수면상태의밴드", "musician_id": 2075, "event_count": 1}, {"name": "호소", "musician_id": 2389, "event_count": 1}], "name": "je'she", "musician_id": 2380}