{"website": "www.facebook.com/imfinety", "genre": "Folk", "event": [{"venue_id": 489, "title": "Waltz with me", "date": "2016-08-31", "time": "20:00", "venue": "살롱 노마드", "lineup": [{"name": "남경민", "musician_id": 701}, {"name": "아임파인땡큐", "musician_id": 2718}, {"name": "어이", "musician_id": 5622}, {"name": "성해빈", "musician_id": 6355}]}, {"venue_id": 712, "title": "멜빵쇼 Wednesday", "date": "2014-12-31", "time": "20:30", "venue": "멜로아", "lineup": [{"name": "아임파인땡큐", "musician_id": 2718}, {"name": "감성주의", "musician_id": 4373}, {"name": "봉미선", "musician_id": 5054}]}, {"venue_id": 784, "title": "라디오엠 x 일생 Stage project", "date": "2014-12-06", "time": "19:00", "venue": "라디오엠", "lineup": [{"name": "아임파인땡큐", "musician_id": 2718}, {"name": "이제형", "musician_id": 3571}, {"name": "데이즈정우", "musician_id": 4376}]}, {"venue_id": 127, "title": "씨클라우드 오픈마이크", "date": "2014-01-21", "time": "20:00", "venue": "c cloud", "lineup": [{"name": "시원한 형", "musician_id": 1115}, {"name": "아임파인땡큐", "musician_id": 2718}, {"name": "오리엔탈 미쓰리", "musician_id": 3148}, {"name": "아날로그다이어리", "musician_id": 3444}]}, {"venue_id": 44, "title": "청춘의서", "date": "2013-09-01", "time": "18:30", "venue": "살롱 바다비 (Salon Badabie)", "lineup": [{"name": "홍현기", "musician_id": 1867}, {"name": "아임파인땡큐", "musician_id": 2718}, {"name": "썬다운쉽", "musician_id": 3030}, {"name": "묵", "musician_id": 3319}]}, {"venue_id": 51, "title": "Between The Cafes", "date": "2013-06-20", "price": "입장료없는 카페공연", "time": "20:00", "venue": "카페 언플러그드 (Cafe Unplugged)", "lineup": [{"name": "김도연", "musician_id": 696}, {"name": "초이", "musician_id": 2071}, {"name": "스며든", "musician_id": 2146}, {"name": "아임파인땡큐", "musician_id": 2718}]}, {"venue_id": 280, "title": "감성달빛 오픈마이크", "date": "2013-06-09", "time": "19:00", "venue": "감성달빛", "lineup": [{"name": "아임파인땡큐", "musician_id": 2718}, {"name": "거닐숨", "musician_id": 2781}, {"name": "신상우", "musician_id": 2916}, {"name": "조광연", "musician_id": 2964}, {"name": "백지희", "musician_id": 3095}]}, {"venue_id": 280, "title": "감성달빛 오픈마이크 공연", "date": "2013-05-14", "time": "19:00", "venue": "감성달빛", "lineup": [{"name": "그냥 찬휘씨", "musician_id": 2229}, {"name": "아임파인땡큐", "musician_id": 2718}, {"name": "신길역로망스", "musician_id": 2731}, {"name": "요아", "musician_id": 2763}, {"name": "윤슬", "musician_id": 2915}]}, {"venue_id": 280, "title": "감성달빛 오픈마이크 공연", "date": "2013-04-16", "time": "19:00", "venue": "감성달빛", "lineup": [{"name": "블랙러시안", "musician_id": 1060}, {"name": "아임파인땡큐", "musician_id": 2718}, {"name": "거닐숨", "musician_id": 2781}, {"name": "엉망", "musician_id": 2792}, {"name": "관자놀이코브라펀치", "musician_id": 2818}, {"name": "윤슬", "musician_id": 2915}, {"name": "신상우", "musician_id": 2916}]}, {"venue_id": 280, "title": "감성달빛 오픈마이크", "date": "2013-02-19", "time": "19:00", "venue": "감성달빛", "lineup": [{"name": "로맨틱모먼트 (Romantic Moment)", "musician_id": 864}, {"name": "이정범", "musician_id": 1176}, {"name": "초이", "musician_id": 2071}, {"name": "오로라스팅", "musician_id": 2390}, {"name": "신현희와 김루트", "musician_id": 2586}, {"name": "아임파인땡큐", "musician_id": 2718}, {"name": "콰지크 디", "musician_id": 2719}, {"name": "샤이", "musician_id": 2720}, {"name": "신길역로망스", "musician_id": 2731}]}], "regular_musician": [{"name": "아임파인땡큐", "musician_id": 2718, "event_count": 10}, {"name": "초이", "musician_id": 2071, "event_count": 2}, {"name": "신길역로망스", "musician_id": 2731, "event_count": 2}, {"name": "거닐숨", "musician_id": 2781, "event_count": 2}, {"name": "윤슬", "musician_id": 2915, "event_count": 2}, {"name": "신상우", "musician_id": 2916, "event_count": 2}, {"name": "관자놀이코브라펀치", "musician_id": 2818, "event_count": 1}, {"name": "오로라스팅", "musician_id": 2390, "event_count": 1}, {"name": "백지희", "musician_id": 3095, "event_count": 1}, {"name": "이정범", "musician_id": 1176, "event_count": 1}, {"name": "조광연", "musician_id": 2964, "event_count": 1}, {"name": "감성주의", "musician_id": 4373, "event_count": 1}, {"name": "데이즈정우", "musician_id": 4376, "event_count": 1}, {"name": "신현희와 김루트", "musician_id": 2586, "event_count": 1}, {"name": "콰지크 디", "musician_id": 2719, "event_count": 1}, {"name": "샤이", "musician_id": 2720, "event_count": 1}, {"name": "블랙러시안", "musician_id": 1060, "event_count": 1}, {"name": "그냥 찬휘씨", "musician_id": 2229, "event_count": 1}, {"name": "김도연", "musician_id": 696, "event_count": 1}, {"name": "남경민", "musician_id": 701, "event_count": 1}, {"name": "봉미선", "musician_id": 5054, "event_count": 1}, {"name": "요아", "musician_id": 2763, "event_count": 1}, {"name": "홍현기", "musician_id": 1867, "event_count": 1}, {"name": "오리엔탈 미쓰리", "musician_id": 3148, "event_count": 1}, {"name": "성해빈", "musician_id": 6355, "event_count": 1}, {"name": "썬다운쉽", "musician_id": 3030, "event_count": 1}, {"name": "시원한 형", "musician_id": 1115, "event_count": 1}, {"name": "로맨틱모먼트 (Romantic Moment)", "musician_id": 864, "event_count": 1}, {"name": "스며든", "musician_id": 2146, "event_count": 1}, {"name": "엉망", "musician_id": 2792, "event_count": 1}, {"name": "이제형", "musician_id": 3571, "event_count": 1}, {"name": "아날로그다이어리", "musician_id": 3444, "event_count": 1}, {"name": "어이", "musician_id": 5622, "event_count": 1}, {"name": "묵", "musician_id": 3319, "event_count": 1}], "name": "아임파인땡큐", "musician_id": 2718}