{"genre": "Pop", "event": [{"venue_id": 130, "title": "[다리살롱 0402] 봄이 오는 재즈 그리고 사랑", "date": "2013-04-02", "price": "1만원 (음료 1잔 포함)", "time": "20:00", "venue": "다리살롱 (가톨릭청년회관)", "lineup": [{"name": "재즈 클라우드", "musician_id": 2825}, {"name": "율", "musician_id": 2826}]}], "album": [{"songs": ["1. Soon We&rsquo;ll Be Found (Radio Edit)"], "albumtitle": "율 : single - Soon We&rsquo;ll Be Found (International) (2009)"}], "regular_musician": [{"name": "재즈 클라우드", "musician_id": 2825, "event_count": 1}, {"name": "율", "musician_id": 2826, "event_count": 1}], "name": "율", "musician_id": 2826}