{"genre": "Pop", "event": [{"venue_id": 173, "title": "2017 부산국제록페스티발 금요일", "date": "2017-08-11", "time": "16:00", "venue": "삼락생태공원", "lineup": [{"name": "내귀에 도청장치", "musician_id": 30}, {"name": "로맨틱펀치 (Romantic Punch)", "musician_id": 143}, {"name": "네미시스 (Nemesis)", "musician_id": 360}, {"name": "언체인드", "musician_id": 1084}, {"name": "이브", "musician_id": 1361}, {"name": "MC 스나이퍼", "musician_id": 2353}, {"name": "제이비드", "musician_id": 4298}, {"name": "뷰티핸섬", "musician_id": 4432}, {"name": "일렉펀트", "musician_id": 5000}, {"name": "우주왕복선싸이드미러", "musician_id": 6084}, {"name": "바나나몽키스패너", "musician_id": 6798}, {"name": "라펠코프", "musician_id": 6854}]}, {"venue_id": 180, "title": "부산클럽투어 11.26 [인터플레이]", "date": "2016-11-26", "price": "현매,예매 10,000원 동일 / 수능생 50% 5000원 (수험표지참)", "time": "19:00", "venue": "부산인터플레이클럽", "lineup": [{"name": "로우필즈", "musician_id": 3153}, {"name": "제이비드", "musician_id": 4298}, {"name": "매거스", "musician_id": 6583}, {"name": "사운드마켓", "musician_id": 6694}, {"name": "굿바이웬디", "musician_id": 6695}]}, {"venue_id": 340, "title": "신해철 메모리얼 콘서트", "date": "2016-10-30", "price": "예매 15,000원 현매 20,000원", "time": "18:00", "venue": "부산 오즈홀 Oz hall", "lineup": [{"name": "헤르츠 (Herz)", "musician_id": 2542}, {"name": "제이비드", "musician_id": 4298}, {"name": "일렉펀트", "musician_id": 5000}, {"name": "리겔 밴드", "musician_id": 5230}, {"name": "비거절크", "musician_id": 6312}]}, {"venue_id": 111, "title": "15회 부산클럽투어", "date": "2014-10-11", "price": "예매 10,000 현매 12,000 4개클럽입장", "time": "18:00", "venue": "부산 무몽크", "lineup": [{"name": "얼룩", "musician_id": 2648}, {"name": "제이비드", "musician_id": 4298}, {"name": "사우스나인", "musician_id": 4492}, {"name": "3볼트", "musician_id": 4589}]}, {"venue_id": 622, "title": "Dopa-Mint Fest", "date": "2014-07-05", "price": "10,000", "time": "18:00", "venue": "도파민트", "lineup": [{"name": "헤르츠 (Herz)", "musician_id": 2542}, {"name": "로우필즈", "musician_id": 3153}, {"name": "뉴트럴리비도", "musician_id": 4296}, {"name": "쓰리볼트 (3volt)", "musician_id": 4297}, {"name": "제이비드", "musician_id": 4298}]}], "regular_musician": [{"name": "제이비드", "musician_id": 4298, "event_count": 5}, {"name": "일렉펀트", "musician_id": 5000, "event_count": 2}, {"name": "헤르츠 (Herz)", "musician_id": 2542, "event_count": 2}, {"name": "로우필즈", "musician_id": 3153, "event_count": 2}, {"name": "사우스나인", "musician_id": 4492, "event_count": 1}, {"name": "바나나몽키스패너", "musician_id": 6798, "event_count": 1}, {"name": "로맨틱펀치 (Romantic Punch)", "musician_id": 143, "event_count": 1}, {"name": "내귀에 도청장치", "musician_id": 30, "event_count": 1}, {"name": "사운드마켓", "musician_id": 6694, "event_count": 1}, {"name": "굿바이웬디", "musician_id": 6695, "event_count": 1}, {"name": "비거절크", "musician_id": 6312, "event_count": 1}, {"name": "MC 스나이퍼", "musician_id": 2353, "event_count": 1}, {"name": "매거스", "musician_id": 6583, "event_count": 1}, {"name": "언체인드", "musician_id": 1084, "event_count": 1}, {"name": "우주왕복선싸이드미러", "musician_id": 6084, "event_count": 1}, {"name": "라펠코프", "musician_id": 6854, "event_count": 1}, {"name": "뉴트럴리비도", "musician_id": 4296, "event_count": 1}, {"name": "쓰리볼트 (3volt)", "musician_id": 4297, "event_count": 1}, {"name": "뷰티핸섬", "musician_id": 4432, "event_count": 1}, {"name": "얼룩", "musician_id": 2648, "event_count": 1}, {"name": "이브", "musician_id": 1361, "event_count": 1}, {"name": "네미시스 (Nemesis)", "musician_id": 360, "event_count": 1}, {"name": "3볼트", "musician_id": 4589, "event_count": 1}, {"name": "리겔 밴드", "musician_id": 5230, "event_count": 1}], "name": "제이비드", "musician_id": 4298}