{"event": [{"venue_id": 137, "title": "썩은 동아줄 페스티벌 [썩동페]", "date": "2014-11-07", "price": "20.000", "time": "19:00", "venue": "프리즘홀", "lineup": [{"name": "고고스타", "musician_id": 22}, {"name": "야마가타 트윅스터 (YamagataTweakster)", "musician_id": 92}, {"name": "러브엑스테레오 ( Love X Stereo )", "musician_id": 954}, {"name": "뉴튼", "musician_id": 2168}, {"name": "리플렉스 (Reflex)", "musician_id": 2599}, {"name": "레인메이커", "musician_id": 4744}, {"name": "DJ Aeltek", "musician_id": 4745}]}], "regular_musician": [{"name": "리플렉스 (Reflex)", "musician_id": 2599, "event_count": 1}, {"name": "레인메이커", "musician_id": 4744, "event_count": 1}, {"name": "DJ Aeltek", "musician_id": 4745, "event_count": 1}, {"name": "고고스타", "musician_id": 22, "event_count": 1}, {"name": "뉴튼", "musician_id": 2168, "event_count": 1}, {"name": "러브엑스테레오 ( Love X Stereo )", "musician_id": 954, "event_count": 1}, {"name": "야마가타 트윅스터 (YamagataTweakster)", "musician_id": 92, "event_count": 1}], "name": "레인메이커", "musician_id": 4744}