{"genre": "Jazz", "event": [{"venue_id": 826, "title": "BLUESHOUSE LIVE", "date": "2016-03-26", "time": "21:30", "venue": "블루스하우스", "lineup": [{"name": "김규하", "musician_id": 5363}, {"name": "김규하 쿼텟", "musician_id": 5985}]}, {"venue_id": 725, "title": "김규하 Quartet", "date": "2016-01-25", "price": "10,000원(음료포함)", "time": "22:00", "venue": "재즈다", "lineup": [{"name": "김규하 쿼텟", "musician_id": 5985}]}, {"venue_id": 826, "title": "BLUESHOUSE LIVE! 김규하 쿼텟", "date": "2016-01-16", "time": "21:30", "venue": "블루스하우스", "lineup": [{"name": "김규하 쿼텟", "musician_id": 5985}]}], "regular_musician": [{"name": "김규하 쿼텟", "musician_id": 5985, "event_count": 3}, {"name": "김규하", "musician_id": 5363, "event_count": 1}], "name": "김규하 쿼텟", "musician_id": 5985}