{"genre": "Jazz", "event": [{"venue_id": 974, "title": "제2회 한국재즈클럽데이 - NS Jazz Band", "date": "2016-01-30", "time": "19:00", "venue": "커피트리 광주", "lineup": [{"name": "김수곤", "musician_id": 6016}, {"name": "NS Jazz Band", "musician_id": 6080}]}, {"venue_id": 725, "title": "유리알유희", "date": "2016-01-17", "price": "10,000원(음료포함)", "time": "20:00", "venue": "재즈다", "lineup": [{"name": "임민수", "musician_id": 4518}, {"name": "유리알 유희", "musician_id": 5053}, {"name": "송미호", "musician_id": 6007}, {"name": "최현정", "musician_id": 6015}, {"name": "김수곤", "musician_id": 6016}, {"name": "김철호", "musician_id": 6017}]}, {"venue_id": 725, "title": "광흥창 Quartet", "date": "2016-01-17", "price": "10,000원(음료포함)", "time": "22:00", "venue": "재즈다", "lineup": [{"name": "박갑윤 트리오", "musician_id": 863}, {"name": "김수곤", "musician_id": 6016}, {"name": "김철호", "musician_id": 6017}, {"name": "광흥창 Quartet", "musician_id": 6018}, {"name": "박갑윤", "musician_id": 6019}, {"name": "최세열", "musician_id": 6020}]}], "regular_musician": [{"name": "김수곤", "musician_id": 6016, "event_count": 3}, {"name": "김철호", "musician_id": 6017, "event_count": 2}, {"name": "NS Jazz Band", "musician_id": 6080, "event_count": 1}, {"name": "광흥창 Quartet", "musician_id": 6018, "event_count": 1}, {"name": "박갑윤", "musician_id": 6019, "event_count": 1}, {"name": "최세열", "musician_id": 6020, "event_count": 1}, {"name": "임민수", "musician_id": 4518, "event_count": 1}, {"name": "송미호", "musician_id": 6007, "event_count": 1}, {"name": "박갑윤 트리오", "musician_id": 863, "event_count": 1}, {"name": "유리알 유희", "musician_id": 5053, "event_count": 1}, {"name": "최현정", "musician_id": 6015, "event_count": 1}], "name": "김수곤", "musician_id": 6016}