{"regular_musician": [{"name": "룸306", "musician_id": 5352, "event_count": 1}, {"name": "플래시 플러드 달링스", "musician_id": 4849, "event_count": 1}, {"name": "75A", "musician_id": 5457, "event_count": 1}], "venue_id": 887, "name": "골목바이닐앤펍", "address": "서울시 용산구 이태원동 557", "lat": "37.5373465705245050", "lng": "126.9871013563114100", "event": [{"venue_id": 887, "title": "골목, VINYL & WACK NIGHT", "date": "2015-08-30", "price": "15000", "time": "19:00", "venue": "골목바이닐앤펍", "lineup": [{"name": "플래시 플러드 달링스", "musician_id": 4849}, {"name": "룸306", "musician_id": 5352}, {"name": "75A", "musician_id": 5457}]}]}